categoriesreader/__init__.py
categoriesreader/categoriesreader.py
constants/__init__.py
constants/constants.py
exceladapter/__init__.py
exceladapter/excelreader.py
exceladapter/excelwriter.py
excelbuilder/__init__.py
excelbuilder/basicbuilder.py
felsim/__init__.py
felsim/__main__.py
felsim/constants.py
felsim/builders/__init__.py
felsim/builders/buildmissingcategories.py
felsim/categoriesreader/__init__.py
felsim/categoriesreader/categoriesreader.py
felsim/config/__init__.py
felsim/config/getactualflowstableconfig.py
felsim/config/getprojectedflowstableconfig.py
felsim/constants/__init__.py
felsim/constants/constants.py
felsim/exceladapter/__init__.py
felsim/exceladapter/excelreader.py
felsim/exceladapter/excelwriter.py
felsim/excelbuilder/__init__.py
felsim/excelbuilder/basicbuilder.py
felsim/extractors/__init__.py
felsim/extractors/extractcash.py
felsim/extractors/extractchecks.py
felsim/extractors/extractcredicoop.py
felsim/extractors/extractcurrentaccounts.py
felsim/extractors/extractestimations.py
felsim/tableextraction/__init__.py
felsim/tableextraction/rowunpacker.py
felsim/tableextraction/tableunpacker.py
felsim/translators/__init__.py
felsim/translators/googletranslator.py
felsimetl-0.1.22.dist-info/METADATA
felsimetl-0.1.22.dist-info/RECORD
felsimetl-0.1.22.dist-info/WHEEL
felsimetl-0.1.22.dist-info/entry_points.txt
felsimetl-0.1.22.dist-info/top_level.txt
tableextraction/__init__.py
tableextraction/rowunpacker.py
tableextraction/tableunpacker.py
translators/__init__.py
translators/googletranslator.py
