Metadata-Version: 2.1
Name: felsimetl
Version: 0.1.22
Summary: ETL for Felsim
Home-page: http://github.com/fedegos/felsimetl
Author: Federico Gosman
Author-email: federico@equipogsm.com
License: MIT
Platform: UNKNOWN
Requires-Dist: openpyxl (==2.4.7)
